inspector_cli/__init__.py
inspector_cli/inspector.py
inspector_cli/config/__init__.py
inspector_cli/config/guide_settings.py
inspector_cli/tools/__init__.py
inspector_cli/tools/analyser/__init__.py
inspector_cli/tools/analyser/analyser.py
inspector_cli/tools/enumerator/__init__.py
inspector_cli/tools/enumerator/enumerator.py
inspector_cli/tools/enumerator/paths/big_list_1273832.txt
inspector_cli/tools/enumerator/paths/common_4746.txt
inspector_cli/tools/enumerator/paths/medium_list_220559.txt
inspector_cli/tools/enumerator/paths/small_list_87664.txt
inspector_cli/tools/enumerator/subdomains/top_110000.txt
inspector_cli/tools/enumerator/subdomains/top_20000.txt
inspector_cli/tools/enumerator/subdomains/top_500.txt
inspector_cli/tools/enumerator/subdomains/top_5000.txt
inspector_cli/tools/enumerator/subdomains/top_50000.txt
inspector_cli/tools/profiler/__init__.py
inspector_cli/tools/profiler/profiler.py
inspector_cli/tools/scanner/__init__.py
inspector_cli/tools/scanner/full_port_list.txt
inspector_cli/tools/scanner/scanner.py
inspector_cli-1.1.3.dist-info/licenses/LICENSE
inspector_cli-1.1.3.dist-info/METADATA
inspector_cli-1.1.3.dist-info/WHEEL
inspector_cli-1.1.3.dist-info/entry_points.txt
inspector_cli-1.1.3.dist-info/top_level.txt
inspector_cli-1.1.3.dist-info/RECORD
