Metadata-Version: 2.4
Name: inspector-cli
Version: 1.1.3
Summary: A modular cybersecurity CLI tool for scanning, recon, and malware analysis.
Home-page: https://github.com/bmp-43/INSPECTOR-CLI.git
Author: Aegis Martin
License: GPLv3
Classifier: Programming Language :: Python :: 3
Classifier: Operating System :: OS Independent
Classifier: License :: OSI Approved :: GNU General Public License v3 (GPLv3)
Requires-Python: >=3.8
License-File: LICENSE
Requires-Dist: requests
Requires-Dist: colorama
Requires-Dist: pyfiglet
Requires-Dist: dnspython
Requires-Dist: python-whois
Requires-Dist: ipwhois
Requires-Dist: aiohttp
Dynamic: author
Dynamic: classifier
Dynamic: description
Dynamic: description-content-type
Dynamic: home-page
Dynamic: license
Dynamic: license-file
Dynamic: requires-dist
Dynamic: requires-python
Dynamic: summary
